telex103c9da12e0/__init__.py
telex103c9da12e0-0.0.2.dist-info/DESCRIPTION.rst
telex103c9da12e0-0.0.2.dist-info/METADATA
telex103c9da12e0-0.0.2.dist-info/RECORD
telex103c9da12e0-0.0.2.dist-info/WHEEL
telex103c9da12e0-0.0.2.dist-info/metadata.json
telex103c9da12e0-0.0.2.dist-info/top_level.txt
