Metadata-Version: 2.0
Name: telex103c9da12e0
Version: 0.0.2
Summary: DO NOT DOWNLOAD! Test respository to track statistics
Home-page: http://github.com/staeiou/telex103c9da12e0
Author: Stuart Geiger
Author-email: stuart@stuartgeiger.com
License: MIT
Platform: UNKNOWN
